[{"Area":"广东","favor":"0","Content":"Python你要不还是把我鲨了吧","forward":"0","Follower":"10","Time":"05月12日 15:58","comment":"0","ID":"磕糖棉花机","Gender":"male"},{"Area":"unknown","favor":"0","Content":"教师资格证求问！高中信息技术现在会不会有Python相关题目啊","forward":"0","Follower":"230","Time":"05月12日 15:56","comment":"0","ID":"陌路尘世","Gender":"female"},{"Area":"unknown","favor":"0","Content":"25、企业级刚需Nginx入门，全面掌握Nginx配置+快速搭建高可用架构\n24、MySQL性能管理及架构设计\n23、前端到后台ThinkPHP开发整站\n22、Python操作三大主流数据库\n\n课程共享➕ 779893973 请备注微博","forward":"0","Follower":"185","Time":"05月12日 15:54","comment":"0","ID":"某某家的某某某","Gender":"female"},{"Area":"韩国","favor":"1","Content":"找个人替我写python 谢谢","forward":"0","Follower":"11","Time":"05月12日 15:53","comment":"3","ID":"努力五八点八八","Gender":"female"},{"Area":"四川","favor":"0","Content":"Python老师上课点名 全程只听见工商7班🙉🙉🙉\n喊得我害怕🙉🙉🙉","forward":"0","Follower":"1390","Time":"05月12日 15:53","comment":"0","ID":"山枕檀痕绾","Gender":"male"},{"Area":"湖北","favor":"5","Content":"这门课（Python）\n听的我想睡觉！","forward":"0","Follower":"777","Time":"05月12日 15:51","comment":"16","ID":"鹿北辰心动小晗LH7","Gender":"male"},{"Area":"unknown","favor":"0","Content":"07 人工智能大数据与复杂系统一月特训班【完结】\n06 Python零基础10天进阶班【完结】\n05. 数据结构与算法-Python语言基础（完结）\n04.万门大学 人工智能与复杂系统60（完结）\n\n课程共享➕ 779893973 请备注微博","forward":"0","Follower":"185","Time":"05月12日 15:51","comment":"0","ID":"某某家的某某某","Gender":"female"},{"Area":"unknown","favor":"0","Content":"15.Android开发必备知识零基础3小时全解锁【完结】\n14.数据结构与算法进阶班【完结】\n13.数据结构与算法Python语言基础【完结】\n12.HTML5CSS3零基础特训班【完结】\n\n课程共享➕ 779893973 请备注微博","forward":"0","Follower":"185","Time":"05月12日 15:50","comment":"0","ID":"某某家的某某某","Gender":"female"},{"Area":"unknown","favor":"0","Content":"04.网易云python\n03.网.易云课堂（总）\n02.价值666元的网易云IOS逆向与安全\n01.60天引爆你打学习力\n\n课程共享➕ 779893973 请备注微博","forward":"0","Follower":"185","Time":"05月12日 15:50","comment":"0","ID":"某某家的某某某","Gender":"female"},{"Area":"unknown","favor":"0","Content":"黑马，上海37期Python全套视频，价值18800！\n黑马web前端\n黑马javeee视频教程云计算与大数据教程12期\n传智黑马java基础  全网独有 idea版的\n\n课程共享➕ 779893973 请备注微博","forward":"0","Follower":"185","Time":"05月12日 15:49","comment":"1","ID":"某某家的某某某","Gender":"female"},{"Area":"unknown","favor":"0","Content":"v01.老男孩Python全栈高级就业班29期（2020年3月最新开班）【8.26更新至第70天】\n07其他网校\nDocker技术入门与实战  第3版.pdf\n17.【龙果学院】从无到有构建大型电商微服务架构-3\n\n课程共享➕ 779893973 请备注微博","forward":"0","Follower":"823","Time":"05月12日 15:48","comment":"0","ID":"sireJin","Gender":"male"},{"Area":"unknown","favor":"0","Content":"2020年_Python_Django基础+实战全套视频【千锋】\n04.黑马\n黑马前端双元基础班(2.0整理版)\n黑马程序员 突破Java面试 - 多线程\n\n课程共享➕ 779893973 请备注微博","forward":"0","Follower":"823","Time":"05月12日 15:47","comment":"0","ID":"sireJin","Gender":"male"},{"Area":"unknown","favor":"0","Content":"深度之眼 Python基础训练营（完结）\n深度之眼 - 人工智能Paper论文精读班（CV方向）\n李航 统计学习方法（完结）\n2020深度之眼全球AI比赛实战训练营\n\n课程共享➕ 779893973 请备注微博","forward":"0","Follower":"185","Time":"05月12日 15:47","comment":"0","ID":"某某家的某某某","Gender":"female"},{"Area":"陕西","favor":"0","Content":"作业展示时我的同学：我用了eviews/spss/Python/xxx模型xx回归、我写了个程序\u2026\n我：Excel","forward":"0","Follower":"50","Time":"05月12日 15:45","comment":"0","ID":"别把希望寄托在别人身上","Gender":"female"},{"Area":"unknown","favor":"0","Content":"【大讲台】大数据实战精英 + 架构师班\n《2020年一线大厂最新Java高级进阶面试题目》含答案解析（152页）\nPython学习-嵩天教授全套\nprometheus企业监控\n\n课程共享➕ 779893973 请备注微博","forward":"0","Follower":"185","Time":"05月12日 15:45","comment":"0","ID":"某某家的某某某","Gender":"female"},{"Area":"unknown","favor":"0","Content":"//@名校公开课bot:哈佛大学计算机科学精品公开课：Python，讲解精彩透彻！深入浅出！通俗易懂！值得好好听听，受益匪浅！","forward":"0","Follower":"468","Time":"05月12日 15:44","comment":"0","ID":"同为后嗣","Gender":"male"},{"Area":"unknown","favor":"0","Content":"【学ypm】网易白帽子训练营（Web安全）\n【千锋Linux】MySQL DBA从入门到精通（65集）\nVMware Virtual SAN 入门到精通(数据中心SDDC，SSD高速集群备份)高清视频教程 18课 压缩\nPython数据处理与分析【完结】\n\n课程共享➕ 779893973 请备注微博","forward":"0","Follower":"823","Time":"05月12日 15:43","comment":"0","ID":"sireJin","Gender":"male"},{"Area":"unknown","favor":"0","Content":"商业分析\n全网最新redis+zookeeper架构师必修课 -- 马士兵教育\n全民一起玩Python 基础篇+提高篇+笔记\n馒头 新媒体运营证书班（完结）\n\n课程共享➕ 779893973 请备注微博","forward":"0","Follower":"823","Time":"05月12日 15:43","comment":"0","ID":"sireJin","Gender":"male"},{"Area":"unknown","favor":"1","Content":"2020黑马C++32期\n开课吧python大数据全栈分析工程师视频教程13期\n开课吧·Java企业级分布式架构师010期Java架构师\n老男孩运维【28期最新完整】\n\n课程共享➕ 779893973 请备注微博","forward":"0","Follower":"823","Time":"05月12日 15:43","comment":"0","ID":"sireJin","Gender":"male"},{"Area":"unknown","favor":"0","Content":"11.华尔街学堂丨三大金融技能工具\u2014\u2014Wind. Excel 与 Python（完结）\n10.华尔街学堂丨Excel实务技能与金融应用（更新中）\n08.尔街学堂丨投行专题：全面解析企业上市（完结）\n\n课程共享mm66z1请备注微博","forward":"0","Follower":"3","Time":"05月12日 15:43","comment":"0","ID":"为何累呢","Gender":"male"},{"Area":"unknown","favor":"0","Content":"46.华尔街学堂\n13.华尔街学堂丨合同审查专题课（完结）\n12.华尔街学堂丨python金融实务从入门到精通（完结）\n\n课程共享mm66z1请备注微博","forward":"0","Follower":"3","Time":"05月12日 15:42","comment":"0","ID":"为何累呢","Gender":"male"},{"Area":"四川","favor":"0","Content":"","forward":"0","Follower":"15","Time":"05月12日 15:42","comment":"0","ID":"Rachelmarsq","Gender":"female"},{"Area":"重庆","favor":"0","Content":"他最好别让我去python了求求了","forward":"0","Follower":"4","Time":"05月12日 15:40","comment":"0","ID":"_煎饺小狗就是偶_","Gender":"female"},{"Area":"unknown","favor":"0","Content":"//@名校公开课bot:哈佛大学计算机科学精品公开课：Python，讲解精彩透彻！深入浅出！通俗易懂！值得好好听听，受益匪浅！","forward":"0","Follower":"158","Time":"05月12日 15:40","comment":"0","ID":"williamfan617","Gender":"male"},{"Area":"unknown","favor":"0","Content":"//@斯坦福桥帮主:值得一看！4小时学透Python入门公开课，Python 所有核心概念讲透了！","forward":"0","Follower":"9","Time":"05月12日 15:38","comment":"0","ID":"小小小YP","Gender":"female"},{"Area":"广东","favor":"2","Content":"听不懂的python希望快点熬过这三十分钟吧","forward":"0","Follower":"242","Time":"05月12日 15:38","comment":"1","ID":"Llsghanz-","Gender":"female"},{"Area":"unknown","favor":"5","Content":"物流专业学python我真的会谢 听天书","forward":"0","Follower":"86","Time":"05月12日 15:32","comment":"8","ID":"终于可以改名字了哈哈哈哈哈","Gender":"female"},{"Area":"上海","favor":"1","Content":"博君一肖娃圈\n有没有人教我python有偿送小v一只","forward":"0","Follower":"170","Time":"05月12日 15:30","comment":"12","ID":"天黑了就把灯打开","Gender":"female"},{"Area":"unknown","favor":"0","Content":"//@名校公开课bot:哈佛大学计算机科学精品公开课：Python，讲解精彩透彻！深入浅出！通俗易懂！值得好好听听，受益匪浅！","forward":"0","Follower":"58","Time":"05月12日 15:29","comment":"0","ID":"二月的信风","Gender":"male"},{"Area":"unknown","favor":"0","Content":"#Python# Python面试的50个经典问答，助你从容通过面试（上）OPython面试的50个经典问答，助你从容通过面试（上）","forward":"0","Follower":"9016","Time":"05月12日 15:28","comment":"0","ID":"学掌门","Gender":"male"},{"Area":"湖北","favor":"0","Content":"为什么Python要讲PPT和答辩\n我是真的会die","forward":"0","Follower":"32","Time":"05月12日 15:23","comment":"1","ID":"YAYA灿和Baek的精神世界","Gender":"female"},{"Area":"unknown","favor":"3","Content":"[2022-05-12]｜CSDN每天值得看｜python\n① 科比投篮预测\u2014\u2014数据处理与分析O网页链接\n② 基于Python的使用numpy进行深度学习O网页链接\n③ Python数据库编程之pymysql详解O网页链接\n查看更多：O网页链接","forward":"6","Follower":"7.3万","Time":"05月12日 15:23","comment":"1","ID":"CSDN每天值得读","Gender":"female"},{"Area":"湖南","favor":"8","Content":"#电竞选手退役后自学转行程序员#今天在破站看到一个中科院博士吐槽他失业吃软饭的一年，在这一年他自学了r语言和python，然后被他师弟师妹吐槽早干嘛去了，所以我在纠结要不要把r语言和python学起来","forward":"0","Follower":"1068","Time":"05月12日 15:19","comment":"6","ID":"是闪闪发光的大狮子呀","Gender":"female"},{"Area":"浙江","favor":"2","Content":"我在学习python","forward":"0","Follower":"2712","Time":"05月12日 15:17","comment":"2","ID":"晚风和海","Gender":"female"},{"Area":"辽宁","favor":"0","Content":"没有一丁点Python基础的hwy\n企图在一周内看懂Python代码完成机器学习大作业\n（OS:问题不大，我有学过两学期Python的小队员，我可以问他）\n结果\u2026\u2026","forward":"0","Follower":"11","Time":"05月12日 15:16","comment":"2","ID":"Naw829","Gender":"female"},{"Area":"四川","favor":"1","Content":"咋就说P自己的照片都没有那么认真过😬\n一个Python 搞疯我\n小红书、CSDN疯狂找资源","forward":"0","Follower":"14","Time":"05月12日 15:12","comment":"0","ID":"湘菜鱼又菜又多余","Gender":"female"},{"Area":"北京","favor":"1","Content":"Python考完想死了","forward":"0","Follower":"290","Time":"05月12日 15:12","comment":"6","ID":"海边兜兜猫","Gender":"female"},{"Area":"山东","favor":"0","Content":"","forward":"0","Follower":"3323","Time":"05月12日 15:11","comment":"0","ID":"IT编程资料馆_看置顶找我","Gender":"male"},{"Area":"新疆","favor":"4","Content":"Python 学得让我越来越烦\n老师疯狂输出让我的脑子要炸了","forward":"0","Follower":"946","Time":"05月12日 15:09","comment":"0","ID":"月亮好美像我一样","Gender":"female"},{"Area":"北京","favor":"0","Content":"python之字符串的三种方法 LCDA数据分析科学院的微博视频","forward":"0","Follower":"2.9万","Time":"05月12日 15:06","comment":"0","ID":"CDA数据分析科学院","Gender":"male"},{"Area":"河南","favor":"18","Content":"","forward":"0","Follower":"20.1万","Time":"05月12日 15:05","comment":"0","ID":"信阳师范学院","Gender":"male"},{"Area":"北京","favor":"0","Content":"python之转义 LCDA数据分析科学院的微博视频","forward":"0","Follower":"2.9万","Time":"05月12日 15:04","comment":"0","ID":"CDA数据分析科学院","Gender":"male"},{"Area":"北京","favor":"6","Content":"python之relu函数 LCDA数据分析科学院的微博视频","forward":"5","Follower":"2.9万","Time":"05月12日 15:03","comment":"0","ID":"CDA数据分析科学院","Gender":"male"},{"Area":"江苏","favor":"2","Content":"考完Python了","forward":"0","Follower":"29","Time":"05月12日 15:02","comment":"0","ID":"集中意念打跑瞌睡虫","Gender":"female"}]