[{"Area":"新加坡","favor":"216","Content":"5418【投稿】癞 露露 lmao哥 Java","forward":"0","Follower":"1.4万","Time":"05月07日 19:54","comment":"27","ID":"嗯男隔空喊话bot","Gender":"female"},{"Area":"黑龙江","favor":"0","Content":"Java饱和了","forward":"0","Follower":"4","Time":"05月07日 19:52","comment":"0","ID":"小Y噗噗-","Gender":"female"},{"Area":"unknown","favor":"0","Content":"#毕业设计##计算机毕业设计##毕设#毕业设计\n接近尾声了，手上的项目快结束了，可以做比较急的，免费加急。\n计算机 软件 课程设计，毕业设计指导，Java，Python，PHP，jsp, web，人脸识别，安卓Android，机器学习，毕设指导，代码讲解指导 。","forward":"0","Follower":"113","Time":"05月07日 19:40","comment":"0","ID":"摇落秋弦","Gender":"female"},{"Area":"广东","favor":"0","Content":"","forward":"0","Follower":"2","Time":"05月07日 19:28","comment":"0","ID":"用户6271176765","Gender":"male"},{"Area":"上海","favor":"1","Content":"首页给我的感觉：戀與java","forward":"0","Follower":"675","Time":"05月07日 19:26","comment":"1","ID":"感觉大家真有趣","Gender":"female"},{"Area":"四川","favor":"6","Content":"笔记本电脑推荐\n机械准研究生，常用matlab AI solidworks，python，Java，大型cad软件等 游戏只玩lol和原神，预算7000左右求推荐 （想要轻薄点的","forward":"0","Follower":"193","Time":"05月07日 19:04","comment":"72","ID":"关景新年快乐","Gender":"male"}]