[{"Area":"unknown","favor":"1","Content":"#毕业设计##计算机毕业设计##毕设#毕业设计\n做好再付，计算机 软件 设计指导，Java，Python，PHP，jsp, web，人脸识别，安卓Android，毕设指导，代码讲解指导 。姐妹们，毕设接近尾声了，还没做的，快来 滴滴我哟","forward":"0","Follower":"2487","Time":"05月06日 08:59","comment":"0","ID":"胖朱迪的半口奶酪","Gender":"female"},{"Area":"unknown","favor":"0","Content":"计算机毕设毕设毕设计算机毕设#毕业设计##计算机毕业设计##毕设#毕业设计\n做好再付，做好再付。计算机 软件 设计，Java，Python，PHP，jsp, web，安卓Android。兄弟姐妹们，可以滴滴我哟","forward":"0","Follower":"113","Time":"05月06日 08:58","comment":"1","ID":"摇落秋弦","Gender":"female"},{"Area":"unknown","favor":"0","Content":"聊聊 Java SPI 机制。O聊聊 Java SPI 机制","forward":"0","Follower":"1135","Time":"05月06日 08:47","comment":"0","ID":"子夜来风","Gender":"male"},{"Area":"广东","favor":"0","Content":"看来是写java 写的太辛苦了","forward":"0","Follower":"16","Time":"05月06日 08:45","comment":"0","ID":"UINIIIIII","Gender":"female"},{"Area":"北京","favor":"18","Content":"","forward":"0","Follower":"20万","Time":"05月06日 08:23","comment":"2","ID":"刘经纬老师","Gender":"male"}]