[{"Area":"unknown","favor":"0","Content":"ptsd了写过python 伪2d小游戏","forward":"0","Follower":"168","Time":"05月08日 18:55","comment":"0","ID":"吃虾大队长_不似小邋遢","Gender":"female"},{"Area":"浙江","favor":"0","Content":"烦死我了我到底为什么要学python真的好无语啊","forward":"0","Follower":"34","Time":"05月08日 18:54","comment":"0","ID":"AkibaOoO","Gender":"male"},{"Area":"unknown","favor":"0","Content":"84 炼数成金：Python数据分析\n83 用地图说话 - Excel数据地图大全\n81 微专业 用户研究：做\u201c会读心术\u201d的用户研究\n80 手绘POP插画完整详解\n79 黄金人脉：让你发掘身边的隐形财富\n\n课程共享582214793请备注微博","forward":"0","Follower":"42","Time":"05月08日 18:53","comment":"0","ID":"情专课程共享","Gender":"female"},{"Area":"unknown","favor":"0","Content":"89 PS教程超级合辑\n88 python web麻瓜编程【完结】\n87 【小象学院】机器学习升级版V\n86 【小象学院】分布式爬虫实战 第二期\n85 【小象学院】Python数据分析 升级版 第二期\n\n课程共享582214793请备注微博","forward":"0","Follower":"42","Time":"05月08日 18:53","comment":"0","ID":"情专课程共享","Gender":"female"},{"Area":"北京","favor":"0","Content":"好像是学生的毕业设计：一个基于opencv、dilb的员工人脸识别考勤系统 （Python 实现）\nhttps:// github.com/inspurer/WorkAttendanceSystem","forward":"1","Follower":"3.4万","Time":"05月08日 18:44","comment":"0","ID":"跟黄哥学编程","Gender":"male"},{"Area":"unknown","favor":"0","Content":"跟我一起念，讨！厌！python!","forward":"0","Follower":"5","Time":"05月08日 18:44","comment":"1","ID":"小邓冲冲冲啊","Gender":"female"},{"Area":"unknown","favor":"0","Content":"Python任务完成！各门学科复习顺利！！发财！！","forward":"0","Follower":"1","Time":"05月08日 18:39","comment":"0","ID":"想不到啥名就随便取吧","Gender":"female"},{"Area":"unknown","favor":"3","Content":"19岁没有好好做的事 22岁了还得重新做\n--自学python有感\n(我恨自己大二的python课天天摸鱼 到处复制粘贴呜呜呜呜)","forward":"0","Follower":"157","Time":"05月08日 18:36","comment":"8","ID":"okay野象","Gender":"female"},{"Area":"unknown","favor":"1","Content":"决定报明年二月份的cfa了\n所以从明天开始\n上午狂看经济学人\n下午狂学cfa和python\n晚上再背背德语\n冲冲冲","forward":"0","Follower":"57","Time":"05月08日 18:35","comment":"2","ID":"wahlloslala","Gender":"female"},{"Area":"河北","favor":"26","Content":"1214号月亮船\n终于搞完了python大作业\n好冷好冷今天入冬了吗这是\n#tyy属于1214#","forward":"0","Follower":"1.1万","Time":"05月08日 18:34","comment":"6","ID":"柯不柯以你把我宠坏","Gender":"female"},{"Area":"上海","favor":"0","Content":"的确//@黄叫兽在拍照:想象中的办公自动化：Python ； 实际的办公自动化：Excel。","forward":"0","Follower":"216","Time":"05月08日 18:33","comment":"0","ID":"三十三lovepeace","Gender":"female"},{"Area":"陕西","favor":"0","Content":"我刚用python写 string s =\"xxxxxxx\"然后报错说无效语法\n想了很久上网搜了下python怎么用字符串\u2026\n好无语 我已经不会写代码","forward":"0","Follower":"19","Time":"05月08日 18:31","comment":"2","ID":"VVVVVplus1","Gender":"male"},{"Area":"unknown","favor":"0","Content":"//@算法时空:这个应该考虑把数组元素转换成下标形式，然后就方便了。以后确实应该先写代码，再出公式。//@时蝇喜箭:@算法时空 //@爱可可-爱生活:handcalcs：将Python代码写的算式/公式转换成Latex公式","forward":"0","Follower":"366","Time":"05月08日 18:29","comment":"0","ID":"欢乐理想者","Gender":"male"},{"Area":"河北","favor":"2","Content":"我每天有一半时间用来思考学外语的为什么要学python，另一半时间用来拖延复习python的进度","forward":"1","Follower":"55","Time":"05月08日 18:26","comment":"0","ID":"rockstar103","Gender":"female"},{"Area":"unknown","favor":"0","Content":"这破python装的我火大 不仅带来了慢慢的开机 还带来了一大堆病毒广告 在我马上要用电脑的时候这种行为到达了顶峰 还有七分钟 祝我成功","forward":"0","Follower":"8","Time":"05月08日 18:23","comment":"3","ID":"giid_","Gender":"female"},{"Area":"unknown","favor":"0","Content":"我真的会死掉，天天赶报告赶到半夜三点，然后躺在床上一个小时睡不着，脑子里，一直胸口一股闷气憋着。大学上了个p，老师让我们学Python，学geoserver，学gdal，学pysal，学openlayers，要资料吗？英文官网上找。啥都不讲，给个螺丝刀让我造航母，妈的。","forward":"0","Follower":"4","Time":"05月08日 18:22","comment":"3","ID":"Amarillo_risotto","Gender":"female"},{"Area":"江苏","favor":"1","Content":"今晚范思哲同名也挽回不了我今天下午被python伤透了的心","forward":"0","Follower":"82","Time":"05月08日 18:16","comment":"0","ID":"Alon额","Gender":"male"},{"Area":"广西","favor":"0","Content":"#手工找年报#\npython是个好东西，可惜我不会","forward":"0","Follower":"115","Time":"05月08日 18:04","comment":"2","ID":"橘子红了five","Gender":"female"},{"Area":"陕西","favor":"0","Content":"你离Python大神的距离就差这三款编程游戏了 L程序员良许的微博视频","forward":"1","Follower":"3486","Time":"05月08日 18:00","comment":"0","ID":"程序员良许","Gender":"male"}]