[{"Area":"unknown","favor":"0","Content":"抱歉，我一眼看到Python就忍不住想笑，as粉丝不愧是以理工男居多。不过这从侧面说明了，我们发声不仅仅是为了五个姑娘，更是为了千千万万普通的打工人和即将成为打工人的无产者，不管是在大厂、在工地或是在车间，都应该享受到劳动权益和个人自由#a-soul成员遭遇公司pua# ✘#a-soul制作委员会致歉#","forward":"0","Follower":"194","Time":"05月15日 15:55","comment":"0","ID":"唐默存Tmc","Gender":"male"},{"Area":"unknown","favor":"1","Content":"sky光遇黑市有没有宝会写python啊，大一的周末作业，应该挺简单的","forward":"0","Follower":"30","Time":"05月15日 15:51","comment":"7","ID":"咸鱼白泷","Gender":"male"},{"Area":"湖北","favor":"0","Content":"PYTHON","forward":"0","Follower":"20","Time":"05月15日 15:50","comment":"2","ID":"ax佬鱼ax","Gender":"female"},{"Area":"江苏","favor":"0","Content":"我真的很崇拜工科IT boy了\n我的wordcloud package就是在python下载不了 但是\n我的神 我的神\n精准找出了我的错误\n解决了我的bug\n也感谢傻乐给我的Anaconda安装包\n只是为啥当时给我pycharm安装包不同时给我这个🙊","forward":"0","Follower":"188","Time":"05月15日 15:47","comment":"0","ID":"Goneandnone23","Gender":"male"},{"Area":"unknown","favor":"0","Content":"#A-SOUL成员遭遇公司PUA# ❗#a-soul制作委员会致歉# ❗ 非常好Python，爱来自瓷器","forward":"0","Follower":"6","Time":"05月15日 15:46","comment":"0","ID":"洗煤球咕咕咕","Gender":"male"},{"Area":"unknown","favor":"0","Content":"我的校园日常自学python第二天，果然和C语言什么还是有很大的区别的@延安大学","forward":"0","Follower":"1","Time":"05月15日 15:45","comment":"0","ID":"名字不要太长像我这样就好66363","Gender":"male"},{"Area":"福建","favor":"4","Content":"31号考python 还要手写编程题 34道我怎么背的完","forward":"0","Follower":"1375","Time":"05月15日 15:44","comment":"6","ID":"StarsI0_","Gender":"female"},{"Area":"unknown","favor":"0","Content":"#A-soul制作委员会致歉# #A-SOUL成员遭遇公司PUA# 希望贵司关注员工身心健康，拒绝pua！ 抽我，我想要Python程序设计","forward":"0","Follower":"7","Time":"05月15日 15:43","comment":"0","ID":"塞纳河的433","Gender":"female"},{"Area":"unknown","favor":"3","Content":"srds这个Python程序设计我真的笑了","forward":"0","Follower":"153","Time":"05月15日 15:40","comment":"0","ID":"OzymandiasOvO","Gender":"male"},{"Area":"福建","favor":"0","Content":"从零开始学python没绷住","forward":"0","Follower":"14","Time":"05月15日 15:40","comment":"0","ID":"缝纫机抖火车","Gender":"male"},{"Area":"浙江","favor":"1","Content":"最近一堆东西要做\n礼拜三不仅要考太极还要考python\n我已经等不及去死啦～","forward":"0","Follower":"154","Time":"05月15日 15:40","comment":"0","ID":"耶耶咕叽咕叽","Gender":"female"},{"Area":"陕西","favor":"0","Content":"","forward":"0","Follower":"95","Time":"05月15日 15:39","comment":"1","ID":"57Friend","Gender":"female"},{"Area":"unknown","favor":"0","Content":"虽然我一直很支持维权，很支持小姐姐们，但你第七条python入门也太逆天了吧什么直男","forward":"0","Follower":"70","Time":"05月15日 15:36","comment":"0","ID":"MEZ123654789","Gender":"female"},{"Area":"unknown","favor":"1","Content":"从零开始学python是吧，难绷😂 😂","forward":"0","Follower":"7","Time":"05月15日 15:35","comment":"0","ID":"流浪玉桂狗","Gender":"male"},{"Area":"安徽","favor":"1","Content":"Python在写一个题目，然后他提示我这个，错在哪了呢","forward":"0","Follower":"118","Time":"05月15日 15:34","comment":"2","ID":"和小丞见面嘛","Gender":"female"},{"Area":"江苏","favor":"2","Content":"今天不看完python不睡觉","forward":"0","Follower":"30","Time":"05月15日 15:32","comment":"3","ID":"super陽_学习版","Gender":"female"},{"Area":"安徽","favor":"1","Content":"Python从入门到入土 get✓","forward":"0","Follower":"87","Time":"05月15日 15:30","comment":"4","ID":"w284w","Gender":"female"},{"Area":"湖北","favor":"0","Content":"","forward":"0","Follower":"20","Time":"05月15日 15:29","comment":"0","ID":"ax佬鱼ax","Gender":"female"},{"Area":"广东","favor":"0","Content":"//@MrExcel:非IT专业学Python，充其量也就是学到个脚本语言水平，做个调包侠而已。。。对于一个办公室数据工作者，如果你对微软全家桶熟练，真的很难找到必须用Python的场景。。。","forward":"0","Follower":"154","Time":"05月15日 15:28","comment":"0","ID":"lianghualin","Gender":"male"},{"Area":"四川","favor":"0","Content":"Python 为什么不设计 do-while 循环结构？\n\n详情==> OPython 为什么不设计 do-while 循环结构？","forward":"0","Follower":"13.5万","Time":"05月15日 15:23","comment":"0","ID":"外刊IT评论","Gender":"male"},{"Area":"湖北","favor":"0","Content":"两天半跑了19个模型。预处理，Python，结果整理，相关性，曲线拟合科学研究就是让你觉得自己做的是不是还不够","forward":"0","Follower":"171","Time":"05月15日 15:20","comment":"2","ID":"蜜蜂蜜蜂疯i","Gender":"female"},{"Area":"河南","favor":"1","Content":"","forward":"0","Follower":"3.2万","Time":"05月15日 15:20","comment":"0","ID":"英语每日一句","Gender":"male"},{"Area":"unknown","favor":"1","Content":"","forward":"0","Follower":"39","Time":"05月15日 15:16","comment":"1","ID":"一小把悲哀的种子","Gender":"female"},{"Area":"unknown","favor":"0","Content":"//@MrExcel:非IT专业学Python，充其量也就是学到个脚本语言水平，做个调包侠而已。。。对于一个办公室数据工作者，如果你对微软全家桶熟练，真的很难找到必须用Python的场景。。。","forward":"0","Follower":"240","Time":"05月15日 15:14","comment":"0","ID":"VITO点王","Gender":"male"},{"Area":"河北","favor":"0","Content":"//@MrExcel:非IT专业学Python，充其量也就是学到个脚本语言水平，做个调包侠而已。。。对于一个办公室数据工作者，如果你对微软全家桶熟练，真的很难找到必须用Python的场景。。。","forward":"0","Follower":"2776","Time":"05月15日 15:09","comment":"0","ID":"洋洋dede意","Gender":"male"},{"Area":"unknown","favor":"1","Content":"不能再被来打脑控了！该学python了！\n来打\n来打\n还在看来打\n你不能这么堕落啊！\n来打\u2026\u2026！","forward":"0","Follower":"291","Time":"05月15日 15:08","comment":"0","ID":"漂过一筐篮子","Gender":"female"},{"Area":"unknown","favor":"1","Content":"Python报错真的可以使人疯狂\n逐渐到了我不能理解的代码领域","forward":"0","Follower":"44","Time":"05月15日 15:07","comment":"0","ID":"霉霉家的小仙女爱上猫狗","Gender":"female"},{"Area":"湖南","favor":"3","Content":"赐我一堆男朋友吧\n一个教我弄电脑一个教我修图 一个教我摄影一个教我Python一个教我运筹学一个教我数据库最后一个当我的提款机帮我买最新的相机吧","forward":"0","Follower":"57","Time":"05月15日 15:07","comment":"5","ID":"大娟啊啊啊啊啊啊","Gender":"female"},{"Area":"天津","favor":"13","Content":"非IT专业学Python，充其量也就是学到个脚本语言水平，做个调包侠而已。。。对于一个办公室数据工作者，如果你对微软全家桶熟练，真的很难找到必须用Python的场景。。。","forward":"6","Follower":"19.7万","Time":"05月15日 15:04","comment":"7","ID":"MrExcel","Gender":"male"},{"Area":"江苏","favor":"0","Content":"我恨，Python好几节课没上了","forward":"0","Follower":"513","Time":"05月15日 15:03","comment":"0","ID":"汤圆拖着贩迪机","Gender":"female"}]