[{"Area":"法国","favor":"0","Content":"昨天做梦梦见塾里教Python课我和小学时期的好朋友去报名，还梦见我们公寓半夜来了国内的医护人员强制全员下楼核酸，还梦见我和twice去鸟不拉屎的地方远足，发现那里都有她们的广告。","forward":"0","Follower":"404","Time":"05月05日 15:55","comment":"2","ID":"THESHALLOWS","Gender":"female"},{"Area":"福建","favor":"2","Content":"我冷暴力...python老师 就不理你就不理你就不理你就不理你","forward":"0","Follower":"25","Time":"05月05日 15:53","comment":"0","ID":"小熱可可_","Gender":"female"},{"Area":"上海","favor":"3","Content":"Python❌\nRPA✔️","forward":"0","Follower":"195","Time":"05月05日 15:50","comment":"1","ID":"在遥远的天边你将化为七道彩虹","Gender":"male"},{"Area":"unknown","favor":"0","Content":"","forward":"0","Follower":"2","Time":"05月05日 15:49","comment":"1","ID":"为何于我","Gender":"female"},{"Area":"江苏","favor":"1","Content":"学python，先给我自己挖坟","forward":"0","Follower":"9","Time":"05月05日 15:43","comment":"0","ID":"Kikoyoiu","Gender":"female"},{"Area":"unknown","favor":"0","Content":"人性爆破\n日天赋认知营辨别源动力清除自我设限持续绽放的三大基石\n量化交易零基础入门系列天掌握Python数据分析\n品牌医生·品牌手册（原版）\n\n更多好课共享：kcc1422 注明微博","forward":"0","Follower":"43","Time":"05月05日 15:37","comment":"1","ID":"杨婕婕婕婕婕","Gender":"female"},{"Area":"江苏","favor":"0","Content":"Python去死吧","forward":"0","Follower":"4","Time":"05月05日 15:36","comment":"0","ID":"luminoustiti","Gender":"female"},{"Area":"unknown","favor":"0","Content":"真烦啊，脑子抽了学计算机\u2026机器学习留作业自己讲解代码，Python留作业自己录视频讲内置函数，人工智能留作业分组讲算法，算法分析留作业分组讲算法吐了","forward":"0","Follower":"4","Time":"05月05日 15:31","comment":"0","ID":"Jayjayw-","Gender":"female"},{"Area":"上海","favor":"0","Content":"好想学python","forward":"0","Follower":"30","Time":"05月05日 15:27","comment":"3","ID":"会不会有月亮","Gender":"female"},{"Area":"unknown","favor":"2","Content":"就是说，大学生学不会python会判多少年","forward":"0","Follower":"31","Time":"05月05日 15:25","comment":"2","ID":"CloudM-","Gender":"female"},{"Area":"河北","favor":"0","Content":"这辈子都不想学python了，好难啊","forward":"1","Follower":"195","Time":"05月05日 15:25","comment":"0","ID":"甜崽小猫咪-","Gender":"female"},{"Area":"unknown","favor":"0","Content":"很紧张 准备考Python了 很没底","forward":"0","Follower":"57","Time":"05月05日 15:24","comment":"0","ID":"没有高鼻梁但有大脸的高中生","Gender":"female"},{"Area":"unknown","favor":"0","Content":"下午：（至六点）\n国际贸易学+大英竞赛\n（ps记得明天写python作业！）","forward":"0","Follower":"2","Time":"05月05日 15:24","comment":"0","ID":"不治司汤达","Gender":"female"},{"Area":"北京","favor":"2","Content":"#领航计划# #Python# Streamlit交互报表设计(7)：上载数据分析出图 L王厚东-数据分析的微博视频","forward":"2","Follower":"5.2万","Time":"05月05日 15:11","comment":"0","ID":"王厚东-数据分析","Gender":"male"},{"Area":"陕西","favor":"0","Content":"我的这b题目 怎么用python写啊 啊？我真的会哭死","forward":"0","Follower":"20","Time":"05月05日 15:10","comment":"0","ID":"阿淳的情绪记录本","Gender":"female"},{"Area":"湖北","favor":"3","Content":"Python怎么这么难\n我真的看不懂","forward":"0","Follower":"144","Time":"05月05日 15:01","comment":"4","ID":"Jz半眠日记","Gender":"female"},{"Area":"广东","favor":"5","Content":"我的Python日常\nerror-百度-debug\nerror-百度-debug\nerror-百度-debug\nerror-error-error\u2026\u2026","forward":"0","Follower":"1284","Time":"05月05日 15:00","comment":"0","ID":"论文灌水大师","Gender":"male"},{"Area":"北京","favor":"0","Content":"","forward":"0","Follower":"1.6万","Time":"05月05日 15:00","comment":"0","ID":"三度编程","Gender":"male"}]