[{"Area":"unknown","favor":"1","Content":"当我把高数学差不多觉得在学一学大物就又可以摆烂一段时间的时候 突然惊醒我还有个线代和一个啥都没学的python\n我就真的开始思考我真的需要这个文凭嘛","forward":"0","Follower":"224","Time":"05月10日 13:00","comment":"0","ID":"陆zzzy","Gender":"female"},{"Area":"unknown","favor":"0","Content":"we are the champions～～\n脑内自动播放\n呜呜呜太感动了弄了半天终于导出这个界面了呜呜呜\n又有动力继续学Python了呜呜呜呜呜呜呜","forward":"0","Follower":"3","Time":"05月10日 12:53","comment":"0","ID":"伯努利-","Gender":"female"},{"Area":"unknown","favor":"1","Content":"python有没有人帮我写期末Python作品？本人一窍不通，有偿","forward":"0","Follower":"3","Time":"05月10日 12:50","comment":"7","ID":"用户蓝调雨夜","Gender":"male"},{"Area":"广东","favor":"0","Content":"所有的电器、软件用户指南写作，都比申论更值得训练，nili python的在线documentation这啰嗦劲儿，看着就累。最后一句话就不能写成，The pre-appending name can avoid the overlapping of global variables with the same name defined from different modules","forward":"0","Follower":"967","Time":"05月10日 12:49","comment":"0","ID":"长安绿秋_爱音客","Gender":"female"},{"Area":"unknown","favor":"0","Content":"学而思\u2022《廖尘-少儿编程Python勤思班Level1五年级零基础入门\n北学鱼\u202c堂《朝夕花\u202c拾深解度\u202c读》\n北学鱼\u202c堂《论语·为政篇》\n\n课程共享➕779893973 请备注微博","forward":"0","Follower":"12","Time":"05月10日 12:47","comment":"0","ID":"青春美丽O心情","Gender":"female"},{"Area":"重庆","favor":"0","Content":"其实这么久了 突然觉得python确实比较简单\u2026\n我不会的根源是数学思维太差了\u2026","forward":"0","Follower":"46","Time":"05月10日 12:47","comment":"0","ID":"莎士比鸦鸦鸦","Gender":"female"},{"Area":"unknown","favor":"0","Content":"//@斌叔儿童编程:我全身都是宝，可以入药//@hdjkgll:这几天从app到python到书，都是宝藏","forward":"0","Follower":"127","Time":"05月10日 12:43","comment":"0","ID":"大大宝贝儿炎炎宝","Gender":"female"},{"Area":"四川","favor":"3","Content":"","forward":"0","Follower":"27","Time":"05月10日 12:39","comment":"8","ID":"拉文克劳之耻的学术垃圾","Gender":"female"},{"Area":"浙江","favor":"4","Content":"美好的一天！！！！\n被Python老师夸真棒芜湖\n就连随机蔬菜也能选到我喜欢的耶耶耶✌️\n如果晚上王者能让我多赢几把那就更好了","forward":"0","Follower":"12","Time":"05月10日 12:33","comment":"3","ID":"一颗大西瓜瓜瓜","Gender":"female"},{"Area":"四川","favor":"0","Content":"五月目标：\n1、找到一份自己还算满意的实习，工资80块钱以上的！\n2、定下论文选题，把需要的数据弄到手，该学python学python","forward":"0","Follower":"87","Time":"05月10日 12:29","comment":"0","ID":"姓丑的","Gender":"male"},{"Area":"unknown","favor":"0","Content":"Python 听我说谢谢你 因为有你 温暖了四季","forward":"0","Follower":"49","Time":"05月10日 12:25","comment":"0","ID":"芝奶布丁","Gender":"female"},{"Area":"北京","favor":"7","Content":"#每日随机一图# by python script","forward":"0","Follower":"3.1万","Time":"05月10日 12:22","comment":"0","ID":"甄星cherish","Gender":"male"},{"Area":"北京","favor":"2","Content":"「GitHub多星项目 ✨」6.7K⭐️ Kivy/python-for-android: 「Turn your Python application into an Android APK」用过的同学来评论下？ O网页链接","forward":"3","Follower":"60.8万","Time":"05月10日 12:21","comment":"0","ID":"Easy","Gender":"male"},{"Area":"unknown","favor":"1","Content":"","forward":"0","Follower":"2","Time":"05月10日 12:16","comment":"0","ID":"话句工","Gender":"female"},{"Area":"湖北","favor":"0","Content":"Python实验课\n我是无情的打字机器","forward":"0","Follower":"11","Time":"05月10日 12:16","comment":"0","ID":"·好想吃菠萝","Gender":"female"},{"Area":"unknown","favor":"0","Content":"Hhq让我python过 捞捞我","forward":"0","Follower":"2","Time":"05月10日 12:03","comment":"7","ID":"摆烂鱼小罐","Gender":"female"},{"Area":"unknown","favor":"1","Content":"留学生作业\n个人写作\n擅长的Java js,Python c ，c++ c# MATLAB r spss..基本上都可以写的，数学物理化学也可以，需要➕ onelock666_","forward":"0","Follower":"1","Time":"05月10日 12:01","comment":"0","ID":"不倒霉的美女","Gender":"female"},{"Area":"unknown","favor":"0","Content":"","forward":"0","Follower":"11","Time":"05月10日 12:00","comment":"0","ID":"六星源课堂","Gender":"female"}]