[{"Area":"unknown","favor":"0","Content":"转：html旋转角度计算,CSS3属性transform详解之（旋转:rotate,缩放:scale,倾斜:skew,移动:translate）：O网页链接","forward":"0","Follower":"27","Time":"05月06日 13:29","comment":"0","ID":"caly_daijing","Gender":"female"},{"Area":"unknown","favor":"0","Content":"#东方财富#：/eastmoney/index.html来自@东方财富网","forward":"0","Follower":"25","Time":"05月06日 13:16","comment":"1","ID":"123昵称不可用123","Gender":"male"},{"Area":"新加坡","favor":"0","Content":"#闪电侠##闪电侠 The Flash# @闪电侠贩 《閃電俠》(#The Flash#) 女星#Danielle Panabaker#表示，當知道Caitlin的安排後，唯一希望知道是否真的如此，因為扮作這樣感覺並不正確，要感到真實及誠懇，必須要確實如此！ ustvmania.blogspot.com/2021/08/flash-season-8.html","forward":"0","Follower":"2.9万","Time":"05月06日 13:06","comment":"1","ID":"USTVMania","Gender":"male"}]