[{"Area":"辽宁","favor":"0","Content":"网易【Java研发实习生】\n急招❗❗❗\nbase北京\n#北京实习##实习#","forward":"0","Follower":"7384","Time":"04月03日 13:58","comment":"0","ID":"今天你找到实习了吗","Gender":"female"},{"Area":"unknown","favor":"0","Content":"","forward":"0","Follower":"20","Time":"04月03日 13:45","comment":"3","ID":"我的铁塔梦828","Gender":"female"},{"Area":"山东","favor":"0","Content":"一起掉头发#java#","forward":"0","Follower":"42","Time":"04月03日 13:36","comment":"4","ID":"_小李头不秃","Gender":"male"},{"Area":"unknown","favor":"1","Content":"Java哈哈哈哈哈","forward":"0","Follower":"181","Time":"04月03日 13:12","comment":"0","ID":"业余草","Gender":"male"}]