[{"Area":"æ±Ÿè‹","favor":"0","Content":"ç¨‹åºå‘˜çš„æ•°å­¦è¯¾\né‡å­¦æ•°æ®ç»“æ„ä¸ç®—æ³•\nå¥ˆå­¦java P7æ¶æ„å¸ˆ\n\nè¯¾ç¨‹å…±äº«ï¼šwwsspe è¯·å¤‡æ³¨å¾®åš","forward":"0","Follower":"60","Time":"04æœˆ25æ—¥ 08:56","comment":"1","ID":"wwsspe","Gender":"female"},{"Area":"unknown","favor":"2","Content":"Javaå“¥æ— å¤„ä¸åœ¨ï¼Œæœ‰ç‚¹ææ€–äº†","forward":"0","Follower":"58","Time":"04æœˆ25æ—¥ 08:55","comment":"6","ID":"Quildren_å…¬å¼","Gender":"female"},{"Area":"æ±Ÿè‹","favor":"0","Content":"é»‘é©¬javaæ¶æ„å¸ˆ\nå¥ˆå­¦Javaèµ„æ·±ç ”å‘å·¥ç¨‹å¸ˆ1æœŸ\nå¼€è¯¾å§åä¼\n\nè¯¾ç¨‹å…±äº«ï¼šwwsspe è¯·å¤‡æ³¨å¾®åš","forward":"0","Follower":"60","Time":"04æœˆ25æ—¥ 08:53","comment":"0","ID":"wwsspe","Gender":"female"},{"Area":"æ±Ÿè‹","favor":"0","Content":"å¾®ä¸“ä¸šæ„å»ºä¸€çº¿äº’è”ç½‘ä¼ä¸šWebå‰ç«¯å…¨æ ˆçŸ¥è¯†å¤§å‚å­¦é™¢é«˜é˜¶ç­javaå¹¶å‘ç¼–ç¨‹é¢è¯•\né‡å­¦æ“ä½œç³»ç»Ÿ\n\nè¯¾ç¨‹å…±äº«ï¼šwwsspe è¯·å¤‡æ³¨å¾®åš","forward":"0","Follower":"60","Time":"04æœˆ25æ—¥ 08:53","comment":"0","ID":"wwsspe","Gender":"female"},{"Area":"unknown","favor":"1","Content":"","forward":"3","Follower":"34.6ä¸‡","Time":"04æœˆ25æ—¥ 08:52","comment":"0","ID":"CSDN","Gender":"male"},{"Area":"å¹¿ä¸œ","favor":"0","Content":"é©¬ä¸­åŒ– é©¬æ”¿ç» é©¬åŸç† é©¬å‘å²//@è¿™ä¸æœ‰æ‰‹å°±è¡Œ_:ã€‚è¿˜æœ‰å¤–å›½æ–‡å­¦//@é“æ¿è‹è‹:å¤ä»£æ–‡å­¦ï¼Œç°ä»£æ–‡å­¦ï¼Œå¤ä»£æ±‰è¯­ï¼Œç°ä»£æ±‰è¯­//@æœ€åä¸€æ¯Tequila:Java C/C++ Python PHP","forward":"1","Follower":"635","Time":"04æœˆ25æ—¥ 08:28","comment":"0","ID":"lycheeeeeÂ·","Gender":"female"},{"Area":"é™•è¥¿","favor":"0","Content":"ğ“†ğ“†Ÿğ“†œğ“†ğ“†ğ“†Ÿğ“†œğ“†\n2022-04-25 è®¡åˆ’ï¼š\nJava IO 2å°æ—¶","forward":"0","Follower":"240","Time":"04æœˆ25æ—¥ 08:22","comment":"0","ID":"alwaysrl_9","Gender":"female"},{"Area":"åŒ—äº¬","favor":"28","Content":"","forward":"2","Follower":"20ä¸‡","Time":"04æœˆ25æ—¥ 08:10","comment":"1","ID":"åˆ˜ç»çº¬è€å¸ˆ","Gender":"male"}]