[{"Area":"天津","favor":"1","Content":"不要再争了，Python，Java，你们都是我的翅膀.jpg（？）","forward":"0","Follower":"32","Time":"04月16日 17:30","comment":"3","ID":"翊Komorebi","Gender":"female"},{"Area":"重庆","favor":"0","Content":"上学期学不懂java这学期学不懂c++ 真搞不懂面向对象 而且老师还选了一本全网找不到答案的课本 真的疯掉","forward":"0","Follower":"70","Time":"04月16日 17:29","comment":"0","ID":"爱狗人士021号","Gender":"female"},{"Area":"unknown","favor":"0","Content":"","forward":"0","Follower":"84.2万","Time":"04月16日 17:24","comment":"0","ID":"佛山兼职全职微招聘网","Gender":"male"},{"Area":"上海","favor":"0","Content":"说起来java都快忘光了","forward":"0","Follower":"4495","Time":"04月16日 17:02","comment":"0","ID":"pinxue","Gender":"male"}]