[{"Area":"unknown","favor":"0","Content":"黑马程序员java教程最新工作流引擎Activiti7基础到进阶，Activiti和Spring框架、SpringBoot整合#哔哩哔哩动画# O黑马程序员java教程最新工作流引擎Activiti7基础到进阶，Activiti和Spring框架、SpringBoot整合","forward":"0","Follower":"266","Time":"04月14日 17:56","comment":"1","ID":"牛奶糖人","Gender":"female"},{"Area":"unknown","favor":"3","Content":"不出意外的话，我下辈子是不会再连着上实验和java了\n希望李老师能容忍我在java课堂上把我的晚饭\u2014\u2014烤冷面吃完\n没有最赶，只有更赶、我真谢、","forward":"0","Follower":"109","Time":"04月14日 17:55","comment":"0","ID":"雨齐一","Gender":"female"},{"Area":"重庆","favor":"0","Content":"一会补考java 室友让我去加java老师给他求情 她们说java老师一直记得我\n：那个黑喜欢打扮的 一天乖桑啦像个网红一样 他上学期就是这么跟我们说的\n笑鼠我了","forward":"0","Follower":"4","Time":"04月14日 17:42","comment":"0","ID":"xelsnzl","Gender":"female"},{"Area":"unknown","favor":"0","Content":"","forward":"0","Follower":"1.5万","Time":"04月14日 17:30","comment":"0","ID":"联合永道官微","Gender":"male"},{"Area":"unknown","favor":"0","Content":"Java//@小丸帽:？//@Adling: 我没听过的新版本//@水蒸气西木: 草//@大荼丸子: 草//@Neo玛丽:？？？？//@黒羽莉夏: 草//@哇大凤: 无缝衔接//@BOOM圣女:草//@志摩凜呐跌西口: 明日香与碇真嗣の奇妙冒险//@魔术师062厨:草//@Ex咕噜喵 :草//@_笑语梦中见 : 爱了//@烤生海星 :？？//@左轮伯伯 : 草","forward":"0","Follower":"128","Time":"04月14日 17:28","comment":"0","ID":"磨砂咖啡机","Gender":"male"},{"Area":"unknown","favor":"0","Content":"肚子好疼\n还在顽强的学java 真的会谢","forward":"0","Follower":"1","Time":"04月14日 17:13","comment":"0","ID":"伤心梁皮-","Gender":"male"},{"Area":"unknown","favor":"2","Content":"徐州工程学院我想问一下Java考试有哪些题型啊","forward":"0","Follower":"1","Time":"04月14日 17:02","comment":"2","ID":"梦醒伤人心lzq","Gender":"male"}]